pyreference/__init__.py
pyreference/gene.py
pyreference/genomic_region.py
pyreference/mirna.py
pyreference/pyreference_config.py
pyreference/reference.py
pyreference/referenceargparse.py
pyreference/settings.py
pyreference/transcript.py
pyreference/utils/__init__.py
pyreference/utils/file_utils.py
pyreference/utils/genomics_utils.py
pyreference/utils/iv_iterators.py
pyreference-0.7.5.data/scripts/pyreference_biotype.py
pyreference-0.7.5.dist-info/LICENSE.txt
pyreference-0.7.5.dist-info/METADATA
pyreference-0.7.5.dist-info/WHEEL
pyreference-0.7.5.dist-info/top_level.txt
pyreference-0.7.5.dist-info/RECORD
