Metadata-Version: 2.1
Name: pyreference
Version: 0.7.5
Summary: Library for working with reference genomes and gene GTF/GFFs
Home-page: https://github.com/SACGF/pyreference
Author: David Lawrence
Author-email: davmlaw@gmail.com
Keywords: genomics,gtf,gff,genome,genes
Classifier: Development Status :: 5 - Production/Stable
Classifier: License :: OSI Approved :: MIT License
Classifier: Programming Language :: Python :: 2.7
Classifier: Programming Language :: Python :: 3.5
Classifier: Programming Language :: Python :: 3.6
Classifier: Programming Language :: Python :: 3.7
Classifier: Programming Language :: Python :: 3.8
Classifier: Programming Language :: Python :: 3.9
Requires-Python: >=2.7, >=3.5
License-File: LICENSE.txt
Requires-Dist: numpy
Requires-Dist: biopython
Requires-Dist: bioutils
Requires-Dist: configargparse
Requires-Dist: deprecation
Requires-Dist: HTSeq
Requires-Dist: lazy
Requires-Dist: pysam
Requires-Dist: pandas
Requires-Dist: seaborn
